{
  "id": "8702229160140785813",
  "title": "Crime Scene:  Recovering Evidence",
  "published": "2015-10-08T12:41:00.000-07:00",
  "updated": "2015-10-08T12:41:51.269-07:00",
  "content": "I haven't had much time to research the news.\u00a0 Of course what I'm looking for is a quick turnover of [crime scene evidence](http://controlroom.blogspot.com/2015/10/men-without-honor.html), such as the transcript of the cockpit voice recordings.\u00a0 Every hour that goes by gives the perpetrators time to mess with the evidence.\u00a0 We know that's incorrect procedure.\u00a0 Any resistance to turning over the evidence should weigh heavily in the investigation to come.",
  "categories": [],
  "author": "Kirby Urner",
  "blog_name": "bizmo_diaries"
}