{
  "id": "5208685280727012451",
  "title": "Rotten Apple Award",
  "published": "2016-07-24T12:59:00.000-07:00",
  "updated": "2016-07-24T13:02:34.013-07:00",
  "content": "And a Rotten Apple award goes to... Mathematics for Elementary School Teachers: A Conceptual Approach. [https://t.co/jpJuX2Mm4A](https://t.co/jpJuX2Mm4A) [#CodeCastle](https://twitter.com/hashtag/CodeCastle?src=hash)\n\u2014 Kirby Urner (@4DsolutionsPDX) [July 24, 2016](https://twitter.com/4DsolutionsPDX/status/757302016280363008)\n\nDumbs it down by withholding [#MedalofFreedom](https://twitter.com/hashtag/MedalofFreedom?src=hash) mathematics, and just sticks wtih the English stuff. No [@BuckyFuller_](https://twitter.com/BuckyFuller_) [https://t.co/CNaUnLQdbx](https://t.co/CNaUnLQdbx)\n\u2014 Kirby Urner (@4DsolutionsPDX) [July 24, 2016](https://twitter.com/4DsolutionsPDX/status/757302620734140416)\n\nLots of room for English [https://t.co/MdAXK3E5lt](https://t.co/MdAXK3E5lt) but no mention of [#MedalofFreedom](https://twitter.com/hashtag/MedalofFreedom?src=hash) American heritage. Rotten Apple award. [@BuckyFullerInst](https://twitter.com/BuckyFullerInst)\n\u2014 Kirby Urner (@4DsolutionsPDX) [July 24, 2016](https://twitter.com/4DsolutionsPDX/status/757303416867598336)",
  "categories": [],
  "author": "Kirby Urner",
  "blog_name": "coffee_shops"
}